Workbook

Sheet Hypothèses
A1: MÉRIDIEN AMÉNAGEMENT & INGÉNIERIE — Hypothèses de chiffrage
A3: Assainissement des eaux usées de Conakry — modèle de chiffrage (ordre de grandeur)
A5: Paramètre | B5: Valeur | C5: Unité | D5: Source / justification
A6: Dotation eaux usées domestiques | B6: 80 | C6: L/hab/j | D6: Ratio usuel pour villes côtières d'Afrique de l'Ouest à faible pression d'eau (à ajuster selon étude de base SEG)
A7: Coefficient de retour à l'égout | B7: 0.8 | C7: sans unité | D7: 80% de l'eau distribuée revient en eaux usées (norme de dimensionnement courante)
A8: Coût réseau de collecte (petit diamètre) | B8: 180000 | C8: USD/km | D8: Coûts régionaux observés sur projets PEAG/PAC Guinée et Afrique de l'Ouest — HYPOTHÈSE À VALIDER
A9: Coût collecteur principal / intercepteur | B9: 450000 | C9: USD/km | D9: Ordre de grandeur projets d'assainissement urbains côtiers — HYPOTHÈSE À VALIDER
A10: Part intercepteurs dans le linéaire total | B10: 0.15 | C10: sans unité | D10: Hypothèse de dimensionnement (15% du réseau en collecteurs principaux)
A11: Coût station de pompage (unitaire) | B11: 350000 | C11: USD/unité | D11: Ordre de grandeur station de refoulement de taille moyenne — HYPOTHÈSE À VALIDER
A12: Densité stations de pompage | B12: 1 | C12: par 3 km² | D12: Hypothèse de maillage selon relief et bassins versants de Conakry
A13: Coût de traitement (boues activées) | B13: 900 | C13: USD/m3/j installé | D13: Fourchette basse-moyenne pour STEP de grande capacité en Afrique de l'Ouest — HYPOTHÈSE À VALIDER
A14: Coût de traitement décentralisé (lagunage/filtres plantés) | B14: 550 | C14: USD/m3/j installé | D14: Solution basse-technicité pour zones périphériques à densité plus faible — HYPOTHÈSE À VALIDER
A15: Taux de change de référence | B15: 8620 | C15: GNF/USD | D15: Taux indicatif à la date de rédaction — à actualiser avant tout usage contractuel
A16: Provision imprévus techniques | B16: 0.15 | C16: sans unité | D16: Provision standard sur travaux de génie civil et réseaux enterrés
A17: Études, contrôle, AMO, supervision | B17: 0.1 | C17: sans unité | D17: Part usuelle des études et de la maîtrise d'œuvre (rôle envisagé pour Méridien)
A19: Toutes les cellules en bleu sur fond jaune pâle sont des hypothèses modifiables. Elles doivent être confirmées par une étude de base technique et un audit de prix avant tout engagement financier.

Sheet Données par zone
A1: Découpage de Conakry — population et dimensionnement par zone
A3: Les 5 zones historiques utilisent les derniers recensements disponibles par commune (RGPH-3 2014, RGPH-4 2025 pour Matam). La ventilation détaillée du RGPH-4 (2025) par les 8 communes récentes n'étant pas encore publiée à la date de rédaction, la zone périphérique est estimée par solde par rapport au total région (3 407 327 hab., RGPH-4, fév. 2026) — À ACTUALISER dès publication officielle.
A5: Zone / Commune(s) | B5: Population (source citée) | C5: Année réf. | D5: Superficie (km²) [estim.] | E5: Taux de couverture actuel [estim.] | F5: Taux de couverture cible | G5: Population additionnelle à raccorder | H5: Linéaire réseau nécessaire (km) | I5: Stations de pompage nécessaires | J5: Débit eaux usées à traiter (m3/j)
A6: Kaloum (centre-ville, port, administration) | B6: 62675 | C6: 2014 (RGPH-3) | D6: 15 | E6: 0.35 | F6: 0.95 | G6: =B6*(F6-E6) -> 37605 | H6: =G6/350 -> 107.44286 | I6: =ROUNDUP(D6*F6/3,0) -> 5 | J6: =G6*Hypothèses!$B$6*Hypothèses!$B$7/1000 -> 2406.72
A7: Dixinn | B7: 137287 | C7: 2014 (RGPH-3) | D7: 12 | E7: 0.25 | F7: 0.9 | G7: =B7*(F7-E7) -> 89236.55 | H7: =G7/350 -> 254.96157 | I7: =ROUNDUP(D7*F7/3,0) -> 4 | J7: =G7*Hypothèses!$B$6*Hypothèses!$B$7/1000 -> 5711.1392
A8: Matam | B8: 177271 | C8: 2025 (RGPH-4) | D8: 8 | E8: 0.2 | F8: 0.9 | G8: =B8*(F8-E8) -> 124089.7 | H8: =G8/350 -> 354.542 | I8: =ROUNDUP(D8*F8/3,0) -> 3 | J8: =G8*Hypothèses!$B$6*Hypothèses!$B$7/1000 -> 7941.7408
A9: Matoto (yc. Gbessia, Tombolia) | B9: 670310 | C9: 2014 (RGPH-3) | D9: 75 | E9: 0.1 | F9: 0.8 | G9: =B9*(F9-E9) -> 469217 | H9: =G9/350 -> 1340.62 | I9: =ROUNDUP(D9*F9/3,0) -> 20 | J9: =G9*Hypothèses!$B$6*Hypothèses!$B$7/1000 -> 30029.888
A10: Ratoma (yc. Sonfonia, Lambanyi) | B10: 653934 | C10: 2014 (RGPH-3) | D10: 90 | E10: 0.08 | F10: 0.75 | G10: =B10*(F10-E10) -> 438135.78 | H10: =G10/350 -> 1251.8165 | I10: =ROUNDUP(D10*F10/3,0) -> 23 | J10: =G10*Hypothèses!$B$6*Hypothèses!$B$7/1000 -> 28040.69
A11: Zone périphérique (Sonfonia, Kagbelen, Sanoyah, Manéah, Kassa et extensions — solde) | B11: =3407327-SUM(B6:B10) -> 1705850 | C11: Solde / RGPH-4 (2025) | D11: 250 | E11: 0.03 | F11: 0.6 | G11: =B11*(F11-E11) -> 972334.5 | H11: =G11/500 -> 1944.669 | I11: =ROUNDUP(D11*F11/4,0) -> 38 | J11: =G11*Hypothèses!$B$6*Hypothèses!$B$7/1000 -> 62229.408
A12: TOTAL CONAKRY | B12: =SUM(B6:B11) -> 3407327 | D12: =SUM(D6:D11) -> 450 | G12: =SUM(G6:G11) -> 2130618.5 | H12: =SUM(H6:H11) -> 5254.0519 | I12: =SUM(I6:I11) -> 93 | J12: =SUM(J6:J11) -> 136359.59

Sheet Phasage et coûts
A1: Phasage proposé et estimation des coûts
A3: Estimation d'ordre de grandeur (classe C — préfaisabilité). À affiner par une étude technico-économique détaillée avant toute décision d'investissement.
A5: Phase | B5: Zones concernées | C5: Horizon | D5: Linéaire réseau (km) | E5: Stations de pompage | F5: Capacité de traitement (m3/j) | G5: Coût travaux (USD) | H5: Coût total avec études + imprévus (USD)
A6: Phase 1 — Urgence centre-ville | B6: Kaloum, Matam, Dixinn | C6: 0-3 ans | D6: =SUM('Données par zone'!H6:H8) -> 716.94643 | E6: =SUM('Données par zone'!I6:I8) -> 12 | F6: =SUM('Données par zone'!J6:J8) -> 16059.6 | G6: =D6*(1-Hypothèses!$B$10)*Hypothèses!$B$8+D6*Hypothèses!$B$10*Hypothèses!$B$9+E6*Hypothèses!$B$11+F6*Hypothèses!$B$13 -> 1.7674033e+08 | H6: =G6*(1+Hypothèses!$B$16+Hypothèses!$B$17) -> 2.2092541e+08
A7: Phase 2 — Consolidation zones denses | B7: Matoto, Ratoma | C7: 3-7 ans | D7: =SUM('Données par zone'!H9:H10) -> 2592.4365 | E7: =SUM('Données par zone'!I9:I10) -> 43 | F7: =SUM('Données par zone'!J9:J10) -> 58070.578 | G7: =D7*(1-Hypothèses!$B$10)*Hypothèses!$B$8+D7*Hypothèses!$B$10*Hypothèses!$B$9+E7*Hypothèses!$B$11+F7*Hypothèses!$B$13 -> 6.3894577e+08 | H7: =G7*(1+Hypothèses!$B$16+Hypothèses!$B$17) -> 7.9868221e+08
A8: Phase 3 — Extension périphérique | B8: Zone périphérique (nouvelles communes) | C8: 7-12 ans | D8: =SUM('Données par zone'!H11:H11) -> 1944.669 | E8: =SUM('Données par zone'!I11:I11) -> 38 | F8: =SUM('Données par zone'!J11:J11) -> 62229.408 | G8: =D8*(1-Hypothèses!$B$10)*Hypothèses!$B$8+D8*Hypothèses!$B$10*Hypothèses!$B$9+E8*Hypothèses!$B$11+F8*Hypothèses!$B$14 -> 4.7632569e+08 | H8: =G8*(1+Hypothèses!$B$16+Hypothèses!$B$17) -> 5.9540711e+08
A9: TOTAL PROJET | D9: =SUM(D6:D8) -> 5254.0519 | E9: =SUM(E6:E8) -> 93 | F9: =SUM(F6:F8) -> 136359.59 | G9: =SUM(G6:G8) -> 1.2920118e+09 | H9: =SUM(H6:H8) -> 1.6150147e+09
A11: Équivalent en GNF (au taux de référence ci-dessus) | H11: =H9*Hypothèses!$B$15 -> 1.3921427e+13
A13: Comparaison de référence : le Projet de Modernisation et d'Extension de la STEP de Conakry (PSTEP), financé par la BID et le Royaume du Maroc, mobilise à lui seul 21,66 M USD (2023-2027) pour la seule composante station d'épuration existante — hors extension du réseau de collecte à l'échelle de la ville.

Sheet Synthèse
A1: Synthèse exécutive — chiffrage
A3: Vue consolidée pour présentation aux partenaires techniques et financiers
A5: Population totale de Conakry (RGPH-4, 2025) | B5: ='Données par zone'!B12 -> 3407327
A6: Population additionnelle à raccorder au réseau | B6: ='Données par zone'!G12 -> 2130618.5
A7: Linéaire de réseau total à construire (km) | B7: ='Phasage et coûts'!D9 -> 5254.0519
A8: Stations de pompage à construire | B8: ='Phasage et coûts'!E9 -> 93
A9: Capacité de traitement additionnelle (m3/j) | B9: ='Phasage et coûts'!F9 -> 136359.59
A10: Coût total du projet, études et imprévus inclus (USD) | B10: ='Phasage et coûts'!H9 -> 1.6150147e+09
A11: Coût total du projet (GNF, équivalent) | B11: ='Phasage et coûts'!H11 -> 1.3921427e+13
A13: Répartition du coût total par phase
A14: Phase | B14: Coût (USD)
A15: ='Phasage et coûts'!A6 -> Phase 1 — Urgence centre-ville | B15: ='Phasage et coûts'!H6 -> 2.2092541e+08
A16: ='Phasage et coûts'!A7 -> Phase 2 — Consolidation zones denses | B16: ='Phasage et coûts'!H7 -> 7.9868221e+08
A17: ='Phasage et coûts'!A8 -> Phase 3 — Extension périphérique | B17: ='Phasage et coûts'!H8 -> 5.9540711e+08
