Workbook

Sheet Synthèse
A1: Synthèse du chiffrage — Péage échangeur Pont 8 Novembre
A3: Hypothèse de majoration
A4: Facteur de majoration retenu (couverture des imprévus) | B4: 3
A5: Appliqué à chaque poste du CAPEX et de l'OPEX (voir feuilles CAPEX / OPEX)
A7: Durée et effectifs
A8: Durée totale de mise en œuvre | B8: =Planning!E10 -> 8
A9: Effectif mobilisé — mise en œuvre (cumulé) | B9: =SUM(MO_CAPEX!D4:D18) -> 28
A10: Effectif permanent — exploitation | B10: =SUM(MO_Exploitation!C4:C9) -> 19
A12: Coûts (majorés)
A13: CAPEX total majoré | B13: =CAPEX!F13 -> 1674960
A14: dont sous-total de base (avant majoration) | B14: =CAPEX!D15 -> 498500 | C14: Pour référence — voir feuille CAPEX
A15: OPEX annuel total majoré | B15: =OPEX!F8 -> 616200
A16: dont sous-total de base (avant majoration) | B16: =OPEX!D9 -> 205400 | C16: Pour référence — voir feuille OPEX
A18: Référence recettes et retour sur investissement
A19: Recettes annuelles estimées (scénario central) | B19: 1100000
A20: Recettes nettes annuelles (recettes - OPEX majoré) | B20: =B19-B15 -> 483800
A21: Retour sur investissement (mois) | B21: =IF(B20<=0,"n/d",B13/(B20/12)) -> 41.545101

Sheet MO_CAPEX
A1: Main d'œuvre qualifiée — phase de mise en œuvre (coût de base, hors majoration)
A2: Chiffres bleus = hypothèses modifiables. Taux de base, avant application du facteur de majoration (voir feuille Synthèse).
A3: Catégorie CAPEX | B3: Poste | C3: Profil / qualification requise | D3: Effectif | E3: Taux mensuel (USD) | F3: Durée (mois) | G3: Coût total (USD)
A4: Études et ingénierie | B4: Chef de projet / ingénieur génie civil | C4: Bac+5 génie civil, 10 ans d'expérience min. | D4: 1 | E4: 3000 | F4: 2.5 | G4: =D4*E4*F4 -> 7500
A5: Études et ingénierie | B5: Ingénieur trafic | C5: Bac+5 ingénierie des transports | D5: 1 | E5: 2200 | F5: 2.5 | G5: =D5*E5*F5 -> 5500
A6: Études et ingénierie | B6: Enquêteurs terrain (comptage O-D) | C6: Techniciens formés au comptage de trafic | D6: 4 | E6: 400 | F6: 1 | G6: =D6*E6*F6 -> 1600
A7: Études et ingénierie | B7: Juriste / expert institutionnel | C7: Bac+5 droit public, consultant | D7: 1 | E7: 2500 | F7: 1 | G7: =D7*E7*F7 -> 2500
A8: Génie civil et portiques | B8: Chef de chantier | C8: Bac+3 génie civil, 8 ans d'expérience | D8: 1 | E8: 1500 | F8: 2.5 | G8: =D8*E8*F8 -> 3750
A9: Génie civil et portiques | B9: Ouvriers qualifiés (maçons, électriciens) | C9: CAP/BEP + expérience chantier | D9: 6 | E9: 500 | F9: 2 | G9: =D9*E9*F9 -> 6000
A10: Génie civil et portiques | B10: Ingénieur électrique | C10: Bac+5 électrotechnique | D10: 1 | E10: 2000 | F10: 1 | G10: =D10*E10*F10 -> 2000
A11: Back-office et plateforme logicielle | B11: Architecte logiciel | C11: Bac+5 informatique, 8 ans d'expérience | D11: 1 | E11: 2500 | F11: 2 | G11: =D11*E11*F11 -> 5000
A12: Back-office et plateforme logicielle | B12: Ingénieur systèmes ANPR/RFID | C12: Spécialiste, 10 ans d'expérience | D12: 1 | E12: 4000 | F12: 1.5 | G12: =D12*E12*F12 -> 6000
A13: Back-office et plateforme logicielle | B13: Développeurs back-end | C13: Bac+4/5 informatique | D13: 2 | E13: 1800 | F13: 2.5 | G13: =D13*E13*F13 -> 9000
A14: Back-office et plateforme logicielle | B14: Ingénieur automatisme (barrières et contrôle d'accès) | C14: Bac+5 automatisme/électromécanique | D14: 1 | E14: 2200 | F14: 1.5 | G14: =D14*E14*F14 -> 3300
A15: Intégration paiement mobile | B15: Développeur intégration (Orange Money / Mobile Money) | C15: Bac+4/5 informatique | D15: 1 | E15: 1800 | F15: 1 | G15: =D15*E15*F15 -> 1800
... A18: Installation et mise en service | B18: Formateurs / accompagnement usagers | C18: Bac+3, expérience formation | D18: 2 | E18: 500 | F18: 1 | G18: =D18*E18*F18 -> 1000
A19: TOTAL MAIN D'ŒUVRE — MISE EN ŒUVRE (base) | G19: =SUM(G4:G18) -> 60500

Sheet MO_Exploitation
A1: Main d'œuvre qualifiée — exploitation continue (coût de base, hors majoration)
A3: Poste | B3: Profil / qualification requise | C3: Effectif | D3: Taux mensuel (USD) | E3: Coût mensuel (USD) | F3: Coût annuel (USD)
A4: Superviseur trafic (responsable tableau de bord) | B4: Bac+4/5, expérience gestion de trafic urbain | C4: 1 | D4: 1200 | E4: =C4*D4 -> 1200 | F4: =E4*12 -> 14400
A5: Agents de péage (voies occasionnelles, encaissement) | B5: Formation encaissement / relation usagers | C5: 6 | D5: 400 | E5: =C5*D5 -> 2400 | F5: =E5*12 -> 28800
A6: Agents de contrôle / interception (postés en aval) | B6: Formation spécifique contrôle routier | C6: 6 | D6: 400 | E6: =C6*D6 -> 2400 | F6: =E6*12 -> 28800
A7: Agents support usagers / centre d'appel | B7: Bac+2, relation client | C7: 3 | D7: 350 | E7: =C7*D7 -> 1050 | F7: =E7*12 -> 12600
A8: Techniciens maintenance équipements et barrières | B8: Bac+2 électronique / électromécanique | C8: 2 | D8: 600 | E8: =C8*D8 -> 1200 | F8: =E8*12 -> 14400
A9: Comptable / gestion recouvrement | B9: Bac+3 comptabilité | C9: 1 | D9: 700 | E9: =C9*D9 -> 700 | F9: =E9*12 -> 8400
A10: TOTAL MAIN D'ŒUVRE — EXPLOITATION (base) | E10: =SUM(E4:E9) -> 8950 | F10: =SUM(F4:F9) -> 107400

Sheet CAPEX
A1: Investissement initial détaillé (CAPEX) — majoré pour couvrir les imprévus
A3: Poste | B3: Main d'œuvre (USD) | C3: Matériel / équipement / autres (USD) | D3: Sous-total de base (USD) | E3: Facteur de majoration | F3: Total majoré (USD)
A4: Études et ingénierie | B4: =SUMIF(MO_CAPEX!$A$4:$A$18,"Études et ingénierie",MO_CAPEX!$G$4:$G$18) -> 17100 | C4: 10000 | D4: =B4+C4 -> 27100 | E4: =Synthèse!$B$4 -> 3 | F4: =D4*E4 -> 81300
A5: Génie civil et portiques | B5: =SUMIF(MO_CAPEX!$A$4:$A$18,"Génie civil et portiques",MO_CAPEX!$G$4:$G$18) -> 11750 | C5: 180000 | D5: =B5+C5 -> 191750 | E5: =Synthèse!$B$4 -> 3 | F5: =D5*E5 -> 575250
A6: Équipements de détection et de contrôle d'accès | B6: 0 | C6: 155000 | D6: =B6+C6 -> 155000 | E6: =Synthèse!$B$4 -> 3 | F6: =D6*E6 -> 465000
A7: Back-office et plateforme logicielle | B7: =SUMIF(MO_CAPEX!$A$4:$A$18,"Back-office et plateforme logicielle",MO_CAPEX!$G$4:$G$18) -> 23300 | C7: 18000 | D7: =B7+C7 -> 41300 | E7: =Synthèse!$B$4 -> 3 | F7: =D7*E7 -> 123900
A8: Intégration paiement mobile | B8: =SUMIF(MO_CAPEX!$A$4:$A$18,"Intégration paiement mobile",MO_CAPEX!$G$4:$G$18) -> 1800 | C8: 12000 | D8: =B8+C8 -> 13800 | E8: =Synthèse!$B$4 -> 3 | F8: =D8*E8 -> 41400
A9: Centre de supervision | B9: 0 | C9: 55000 | D9: =B9+C9 -> 55000 | E9: =Synthèse!$B$4 -> 3 | F9: =D9*E9 -> 165000
A10: Installation et mise en service | B10: =SUMIF(MO_CAPEX!$A$4:$A$18,"Installation et mise en service",MO_CAPEX!$G$4:$G$18) -> 6550 | C10: 8000 | D10: =B10+C10 -> 14550 | E10: =Synthèse!$B$4 -> 3 | F10: =D10*E10 -> 43650
A11: Sous-total majoré avant contingence | F11: =SUM(F4:F10) -> 1495500
A12: Contingence additionnelle (aléas de mise en œuvre) | E12: 0.12 | F12: =F11*E12 -> 179460
A13: TOTAL CAPEX (majoré + contingence) | F13: =F11+F12 -> 1674960
A15: Pour mémoire — sous-total de base avant majoration | D15: =SUM(D4:D10) -> 498500

Sheet OPEX
A1: Coûts d'exploitation annuels détaillés (OPEX) — majorés pour couvrir les imprévus
A3: Poste | B3: Main d'œuvre (USD/an) | C3: Autres coûts (USD/an) | D3: Sous-total de base (USD/an) | E3: Facteur de majoration | F3: Total majoré (USD/an)
A4: Maintenance des équipements | B4: 0 | C4: 65000 | D4: =B4+C4 -> 65000 | E4: =Synthèse!$B$4 -> 3 | F4: =D4*E4 -> 195000
A5: Licences logicielles | B5: 0 | C5: 18000 | D5: =B5+C5 -> 18000 | E5: =Synthèse!$B$4 -> 3 | F5: =D5*E5 -> 54000
A6: Connectivité et hébergement | B6: 0 | C6: 15000 | D6: =B6+C6 -> 15000 | E6: =Synthèse!$B$4 -> 3 | F6: =D6*E6 -> 45000
A7: Personnel d'exploitation | B7: =MO_Exploitation!F10 -> 107400 | C7: 0 | D7: =B7+C7 -> 107400 | E7: =Synthèse!$B$4 -> 3 | F7: =D7*E7 -> 322200
A8: TOTAL OPEX majoré (hors commissions de paiement) | F8: =SUM(F4:F7) -> 616200
A9: Pour mémoire — sous-total de base avant majoration | D9: =SUM(D4:D7) -> 205400
A11: Frais de paiement mobile (commissions de transaction) | F11: Variable — ~1 à 2% des recettes encaissées

Sheet Planning
A1: Durée du projet — phasage de mise en œuvre
A3: Phase | B3: Contenu | C3: Durée retenue (mois) | D3: Début (mois) | E3: Fin (mois)
A4: 1. Études préalables | B4: Comptages de trafic, enquête origine-destination, étude d'impact, cadrage juridique | C4: 2.5 | D4: 0 | E4: =D4+C4 -> 2.5
A5: 2. Conception détaillée | B5: Dimensionnement des portiques, choix des équipements, architecture logicielle | C5: 2 | D5: =E4 -> 2.5 | E5: =D5+C5 -> 4.5
A6: 3. Phase pilote | B6: Installation du dispositif, tests techniques, exploitation gratuite | C6: 2.5 | D6: =E5 -> 4.5 | E6: =D6+C6 -> 7
A7: 4. Mise en service tarifée | B7: Introduction progressive de la tarification, période de grâce | C7: 1 | D7: =E6 -> 7 | E7: =D7+C7 -> 8
A8: 5. Exploitation et extension | B8: Montée en charge, évaluation, étude d'extension | C8: Continu | D8: =E7 -> 8 | E8: —
A10: DURÉE TOTALE DE MISE EN ŒUVRE (avant exploitation) | E10: =E7 -> 8
